SDS_Serverless_Data_Shield/__init__.py
SDS_Serverless_Data_Shield/cleanUp.py
SDS_Serverless_Data_Shield/cryptoHandler.py
SDS_Serverless_Data_Shield/secureContext.py
SDS_Serverless_Data_Shield/secureVar.py
SDS_Serverless_Data_Shield/sds_mem_tools/CMakeLists.txt
SDS_Serverless_Data_Shield/sds_mem_tools/README.md
SDS_Serverless_Data_Shield/sds_mem_tools/sdsmemtools.cpython-313-darwin.so
SDS_Serverless_Data_Shield/sds_mem_tools/src/main.c
SDS_Serverless_Data_Shield/sds_mem_tools/src/memview_methods.c
SDS_Serverless_Data_Shield/sds_mem_tools/src/memview_type.c
SDS_Serverless_Data_Shield/sds_mem_tools/src/mpointer.c
SDS_Serverless_Data_Shield/sds_mem_tools/src/mpointer_methods.c
SDS_Serverless_Data_Shield/sds_mem_tools/src/include/memview.h
SDS_Serverless_Data_Shield/sds_mem_tools/src/include/mpointer.h
sds_serverless_data_shield-0.1.27.dist-info/licenses/LICENSE
sds_serverless_data_shield-0.1.27.dist-info/METADATA
sds_serverless_data_shield-0.1.27.dist-info/WHEEL
sds_serverless_data_shield-0.1.27.dist-info/top_level.txt
sds_serverless_data_shield-0.1.27.dist-info/RECORD
