Metadata-Version: 2.4
Name: SDS_Serverless_Data_Shield
Version: 0.1.27
Summary: Ephemeral key-based encryption for secure serverless function execution
Author: Scott Choo, Sukyum Ahn, Gyupil Ko, Jaeho Lee
License: MIT
Project-URL: Repository, https://github.com/cau-cslab/SDS-Serverless-Data-Shield
Keywords: serverless,ephemeral encryption,memory security,secure lambda,data sanitization
Classifier: Development Status :: 3 - Alpha
Classifier: Intended Audience :: Developers
Classifier: Topic :: Security :: Cryptography
Classifier: License :: OSI Approved :: MIT License
Classifier: Programming Language :: Python :: 3
Classifier: Programming Language :: Python :: 3.8
Classifier: Programming Language :: Python :: 3.9
Classifier: Programming Language :: Python :: 3.10
Classifier: Programming Language :: Python :: 3.11
Requires-Python: >=3.8
License-File: LICENSE
Requires-Dist: cryptography>=41.0.0
Dynamic: license-file
